README.md
setup.py
univoucher/__init__.py
univoucher/models.py
univoucher.egg-info/PKG-INFO
univoucher.egg-info/SOURCES.txt
univoucher.egg-info/dependency_links.txt
univoucher.egg-info/requires.txt
univoucher.egg-info/top_level.txt
univoucher/local/__init__.py
univoucher/local/vouchers.py