Metadata-Version: 2.1
Name: univoucher
Version: 2.0.0
Summary: Programmatically create UniFi Guest vouchers
Home-page: https://github.com/Perzan/univoucher
Author: Perzan
Author-email: PerzanDevelopment@gmail.com
License: UNKNOWN
Platform: UNKNOWN
